{
  "Baseline": {
    "Display 1": {
      "FontFamily": {
        "$extensions": {
          "com.figma.scopes": [
            "FONT_FAMILY"
          ],
          "com.figma.hiddenFromPublishing": true
        },
        "$type": "text",
        "$value": "{Typography.Font Family.Plain}"
      },
      "Tracking": {
        "$extensions": {
          "com.figma.scopes": [
            "LETTER_SPACING",
            "PARAGRAPH_SPACING",
            "PARAGRAPH_INDENT"
          ],
          "com.figma.hiddenFromPublishing": true
        },
        "$type": "number",
        "$value": "{Typography.Tracking.None}"
      },
      "LineHeight": {
        "$extensions": {
          "com.figma.scopes": [
            "LINE_HEIGHT"
          ],
          "com.figma.hiddenFromPublishing": true
        },
        "$type": "number",
        "$value": "{Typography.Line Height.700}"
      },
      "FontSize": {
        "$extensions": {
          "com.figma.scopes": [
            "FONT_SIZE"
          ],
          "com.figma.hiddenFromPublishing": true
        },
        "$type": "number",
        "$value": "{Typography.Font Size.580}"
      }
    },
    "Display 2": {
      "FontFamily": {
        "$extensions": {
          "com.figma.scopes": [
            "FONT_FAMILY"
          ],
          "com.figma.hiddenFromPublishing": true
        },
        "$type": "text",
        "$value": "{Typography.Font Family.Plain}"
      },
      "Tracking": {
        "$extensions": {
          "com.figma.scopes": [
            "LETTER_SPACING",
            "PARAGRAPH_SPACING",
            "PARAGRAPH_INDENT"
          ],
          "com.figma.hiddenFromPublishing": true
        },
        "$type": "number",
        "$value": "{Typography.Tracking.None}"
      },
      "FontSize": {
        "$extensions": {
          "com.figma.scopes": [
            "FONT_SIZE"
          ],
          "com.figma.hiddenFromPublishing": true
        },
        "$type": "number",
        "$value": "{Typography.Font Size.520}"
      },
      "LineHeight": {
        "$extensions": {
          "com.figma.scopes": [
            "LINE_HEIGHT"
          ],
          "com.figma.hiddenFromPublishing": true
        },
        "$type": "number",
        "$value": "{Typography.Line Height.620}"
      }
    },
    "Display 3": {
      "FontFamily": {
        "$extensions": {
          "com.figma.scopes": [
            "FONT_FAMILY"
          ],
          "com.figma.hiddenFromPublishing": true
        },
        "$type": "text",
        "$value": "{Typography.Font Family.Plain}"
      },
      "LineHeight": {
        "$extensions": {
          "com.figma.scopes": [
            "LINE_HEIGHT"
          ],
          "com.figma.hiddenFromPublishing": true
        },
        "$type": "number",
        "$value": "{Typography.Line Height.540}"
      },
      "FontSize": {
        "$extensions": {
          "com.figma.scopes": [
            "FONT_SIZE"
          ],
          "com.figma.hiddenFromPublishing": true
        },
        "$type": "number",
        "$value": "{Typography.Font Size.450}"
      },
      "Tracking": {
        "$extensions": {
          "com.figma.scopes": [
            "LETTER_SPACING",
            "PARAGRAPH_SPACING",
            "PARAGRAPH_INDENT"
          ],
          "com.figma.hiddenFromPublishing": true
        },
        "$type": "number",
        "$value": "{Typography.Tracking.None}"
      }
    },
    "Display 4": {
      "FontFamily": {
        "$extensions": {
          "com.figma.scopes": [
            "FONT_FAMILY"
          ],
          "com.figma.hiddenFromPublishing": true
        },
        "$type": "text",
        "$value": "{Typography.Font Family.Plain}"
      },
      "FontSize": {
        "$extensions": {
          "com.figma.scopes": [
            "FONT_SIZE"
          ],
          "com.figma.hiddenFromPublishing": true
        },
        "$type": "number",
        "$value": "{Typography.Font Size.400}"
      },
      "LineHeight": {
        "$extensions": {
          "com.figma.scopes": [
            "LINE_HEIGHT"
          ],
          "com.figma.hiddenFromPublishing": true
        },
        "$type": "number",
        "$value": "{Typography.Line Height.480}"
      },
      "Tracking": {
        "$extensions": {
          "com.figma.scopes": [
            "LETTER_SPACING",
            "PARAGRAPH_SPACING",
            "PARAGRAPH_INDENT"
          ],
          "com.figma.hiddenFromPublishing": true
        },
        "$type": "number",
        "$value": "{Typography.Tracking.None}"
      }
    },
    "H1": {
      "FontFamily": {
        "$extensions": {
          "com.figma.scopes": [
            "FONT_FAMILY"
          ],
          "com.figma.hiddenFromPublishing": true
        },
        "$type": "text",
        "$value": "{Typography.Font Family.Plain}"
      },
      "FontSize": {
        "$extensions": {
          "com.figma.scopes": [
            "FONT_SIZE"
          ],
          "com.figma.hiddenFromPublishing": true
        },
        "$type": "number",
        "$value": "{Typography.Font Size.360}"
      },
      "LineHeight": {
        "$extensions": {
          "com.figma.scopes": [
            "LINE_HEIGHT"
          ],
          "com.figma.hiddenFromPublishing": true
        },
        "$type": "number",
        "$value": "{Typography.Line Height.440}"
      },
      "Tracking": {
        "$extensions": {
          "com.figma.scopes": [
            "LETTER_SPACING",
            "PARAGRAPH_SPACING",
            "PARAGRAPH_INDENT"
          ],
          "com.figma.hiddenFromPublishing": true
        },
        "$type": "number",
        "$value": "{Typography.Tracking.None}"
      }
    },
    "H2": {
      "FontFamily": {
        "$extensions": {
          "com.figma.scopes": [
            "FONT_FAMILY"
          ],
          "com.figma.hiddenFromPublishing": true
        },
        "$type": "text",
        "$value": "{Typography.Font Family.Plain}"
      },
      "FontSize": {
        "$extensions": {
          "com.figma.scopes": [
            "FONT_SIZE"
          ],
          "com.figma.hiddenFromPublishing": true
        },
        "$type": "number",
        "$value": "{Typography.Font Size.320}"
      },
      "LineHeight": {
        "$extensions": {
          "com.figma.scopes": [
            "LINE_HEIGHT"
          ],
          "com.figma.hiddenFromPublishing": true
        },
        "$type": "number",
        "$value": "{Typography.Line Height.390}"
      },
      "Tracking": {
        "$extensions": {
          "com.figma.scopes": [
            "LETTER_SPACING",
            "PARAGRAPH_SPACING",
            "PARAGRAPH_INDENT"
          ],
          "com.figma.hiddenFromPublishing": true
        },
        "$type": "number",
        "$value": "{Typography.Tracking.None}"
      }
    },
    "H3": {
      "FontFamily": {
        "$extensions": {
          "com.figma.scopes": [
            "FONT_FAMILY"
          ],
          "com.figma.hiddenFromPublishing": true
        },
        "$type": "text",
        "$value": "{Typography.Font Family.Plain}"
      },
      "FontSize": {
        "$extensions": {
          "com.figma.scopes": [
            "FONT_SIZE"
          ],
          "com.figma.hiddenFromPublishing": true
        },
        "$type": "number",
        "$value": "{Typography.Font Size.280}"
      },
      "LineHeight": {
        "$extensions": {
          "com.figma.scopes": [
            "LINE_HEIGHT"
          ],
          "com.figma.hiddenFromPublishing": true
        },
        "$type": "number",
        "$value": "{Typography.Line Height.340}"
      },
      "Tracking": {
        "$extensions": {
          "com.figma.scopes": [
            "LETTER_SPACING",
            "PARAGRAPH_SPACING",
            "PARAGRAPH_INDENT"
          ],
          "com.figma.hiddenFromPublishing": true
        },
        "$type": "number",
        "$value": "{Typography.Tracking.None}"
      }
    },
    "H4": {
      "FontFamily": {
        "$extensions": {
          "com.figma.scopes": [
            "FONT_FAMILY"
          ],
          "com.figma.hiddenFromPublishing": true
        },
        "$type": "text",
        "$value": "{Typography.Font Family.Plain}"
      },
      "FontSize": {
        "$extensions": {
          "com.figma.scopes": [
            "FONT_SIZE"
          ],
          "com.figma.hiddenFromPublishing": true
        },
        "$type": "number",
        "$value": "{Typography.Font Size.250}"
      },
      "LineHeight": {
        "$extensions": {
          "com.figma.scopes": [
            "LINE_HEIGHT"
          ],
          "com.figma.hiddenFromPublishing": true
        },
        "$type": "number",
        "$value": "{Typography.Line Height.300}"
      },
      "Tracking": {
        "$extensions": {
          "com.figma.scopes": [
            "LETTER_SPACING",
            "PARAGRAPH_SPACING",
            "PARAGRAPH_INDENT"
          ],
          "com.figma.hiddenFromPublishing": true
        },
        "$type": "number",
        "$value": "{Typography.Tracking.None}"
      }
    },
    "H5": {
      "FontFamily": {
        "$extensions": {
          "com.figma.scopes": [
            "FONT_FAMILY"
          ],
          "com.figma.hiddenFromPublishing": true
        },
        "$type": "text",
        "$value": "{Typography.Font Family.Plain}"
      },
      "FontSize": {
        "$extensions": {
          "com.figma.scopes": [
            "FONT_SIZE"
          ],
          "com.figma.hiddenFromPublishing": true
        },
        "$type": "number",
        "$value": "{Typography.Font Size.220}"
      },
      "LineHeight": {
        "$extensions": {
          "com.figma.scopes": [
            "LINE_HEIGHT"
          ],
          "com.figma.hiddenFromPublishing": true
        },
        "$type": "number",
        "$value": "{Typography.Line Height.270}"
      },
      "Tracking": {
        "$extensions": {
          "com.figma.scopes": [
            "LETTER_SPACING",
            "PARAGRAPH_SPACING",
            "PARAGRAPH_INDENT"
          ],
          "com.figma.hiddenFromPublishing": true
        },
        "$type": "number",
        "$value": "{Typography.Tracking.None}"
      }
    },
    "H6": {
      "FontFamily": {
        "$extensions": {
          "com.figma.scopes": [
            "FONT_FAMILY"
          ],
          "com.figma.hiddenFromPublishing": true
        },
        "$type": "text",
        "$value": "{Typography.Font Family.Plain}"
      },
      "FontSize": {
        "$extensions": {
          "com.figma.scopes": [
            "FONT_SIZE"
          ],
          "com.figma.hiddenFromPublishing": true
        },
        "$type": "number",
        "$value": "{Typography.Font Size.200}"
      },
      "LineHeight": {
        "$extensions": {
          "com.figma.scopes": [
            "LINE_HEIGHT"
          ],
          "com.figma.hiddenFromPublishing": true
        },
        "$type": "number",
        "$value": "{Typography.Line Height.250}"
      },
      "Tracking": {
        "$extensions": {
          "com.figma.scopes": [
            "LETTER_SPACING",
            "PARAGRAPH_SPACING",
            "PARAGRAPH_INDENT"
          ],
          "com.figma.hiddenFromPublishing": true
        },
        "$type": "number",
        "$value": "{Typography.Tracking.None}"
      }
    },
    "Title": {
      "FontFamily": {
        "$extensions": {
          "com.figma.scopes": [
            "FONT_FAMILY"
          ],
          "com.figma.hiddenFromPublishing": true
        },
        "$type": "text",
        "$value": "{Typography.Font Family.Plain}"
      },
      "FontSize": {
        "$extensions": {
          "com.figma.scopes": [
            "FONT_SIZE"
          ],
          "com.figma.hiddenFromPublishing": true
        },
        "$type": "number",
        "$value": "{Typography.Font Size.180}"
      },
      "LineHeight": {
        "$extensions": {
          "com.figma.scopes": [
            "LINE_HEIGHT"
          ],
          "com.figma.hiddenFromPublishing": true
        },
        "$type": "number",
        "$value": "{Typography.Line Height.250}"
      },
      "Tracking": {
        "$extensions": {
          "com.figma.scopes": [
            "LETTER_SPACING",
            "PARAGRAPH_SPACING",
            "PARAGRAPH_INDENT"
          ],
          "com.figma.hiddenFromPublishing": true
        },
        "$type": "number",
        "$value": "{Typography.Tracking.None}"
      }
    },
    "Subtitle": {
      "FontFamily": {
        "$extensions": {
          "com.figma.scopes": [
            "FONT_FAMILY"
          ],
          "com.figma.hiddenFromPublishing": true
        },
        "$type": "text",
        "$value": "{Typography.Font Family.Plain}"
      },
      "FontSize": {
        "$extensions": {
          "com.figma.scopes": [
            "FONT_SIZE"
          ],
          "com.figma.hiddenFromPublishing": true
        },
        "$type": "number",
        "$value": "{Typography.Font Size.160}"
      },
      "LineHeight": {
        "$extensions": {
          "com.figma.scopes": [
            "LINE_HEIGHT"
          ],
          "com.figma.hiddenFromPublishing": true
        },
        "$type": "number",
        "$value": "{Typography.Line Height.200}"
      },
      "Tracking": {
        "$extensions": {
          "com.figma.scopes": [
            "LETTER_SPACING",
            "PARAGRAPH_SPACING",
            "PARAGRAPH_INDENT"
          ],
          "com.figma.hiddenFromPublishing": true
        },
        "$type": "number",
        "$value": "{Typography.Tracking.None}"
      }
    },
    "Label-lg": {
      "FontFamily": {
        "$extensions": {
          "com.figma.scopes": [
            "FONT_FAMILY"
          ],
          "com.figma.hiddenFromPublishing": true
        },
        "$type": "text",
        "$value": "{Typography.Font Family.Plain}"
      },
      "FontSize": {
        "$extensions": {
          "com.figma.scopes": [
            "FONT_SIZE"
          ],
          "com.figma.hiddenFromPublishing": true
        },
        "$type": "number",
        "$value": "{Typography.Font Size.140}"
      },
      "LineHeight": {
        "$extensions": {
          "com.figma.scopes": [
            "LINE_HEIGHT"
          ],
          "com.figma.hiddenFromPublishing": true
        },
        "$type": "number",
        "$value": "{Typography.Line Height.200}"
      },
      "Tracking": {
        "$extensions": {
          "com.figma.scopes": [
            "LETTER_SPACING",
            "PARAGRAPH_SPACING",
            "PARAGRAPH_INDENT"
          ],
          "com.figma.hiddenFromPublishing": true
        },
        "$type": "number",
        "$value": "{Typography.Tracking.None}"
      }
    },
    "Label-md": {
      "FontFamily": {
        "$extensions": {
          "com.figma.scopes": [
            "FONT_FAMILY"
          ],
          "com.figma.hiddenFromPublishing": true
        },
        "$type": "text",
        "$value": "{Typography.Font Family.Plain}"
      },
      "FontSize": {
        "$extensions": {
          "com.figma.scopes": [
            "FONT_SIZE"
          ],
          "com.figma.hiddenFromPublishing": true
        },
        "$type": "number",
        "$value": "{Typography.Font Size.120}"
      },
      "LineHeight": {
        "$extensions": {
          "com.figma.scopes": [
            "LINE_HEIGHT"
          ],
          "com.figma.hiddenFromPublishing": true
        },
        "$type": "number",
        "$value": "{Typography.Line Height.160}"
      },
      "Tracking": {
        "$extensions": {
          "com.figma.scopes": [
            "LETTER_SPACING",
            "PARAGRAPH_SPACING",
            "PARAGRAPH_INDENT"
          ],
          "com.figma.hiddenFromPublishing": true
        },
        "$type": "number",
        "$value": "{Typography.Tracking.None}"
      }
    },
    "Label-sm": {
      "FontFamily": {
        "$extensions": {
          "com.figma.scopes": [
            "FONT_FAMILY"
          ],
          "com.figma.hiddenFromPublishing": true
        },
        "$type": "text",
        "$value": "{Typography.Font Family.Plain}"
      },
      "FontSize": {
        "$extensions": {
          "com.figma.scopes": [
            "FONT_SIZE"
          ],
          "com.figma.hiddenFromPublishing": true
        },
        "$type": "number",
        "$value": "{Typography.Font Size.110}"
      },
      "LineHeight": {
        "$extensions": {
          "com.figma.scopes": [
            "LINE_HEIGHT"
          ],
          "com.figma.hiddenFromPublishing": true
        },
        "$type": "number",
        "$value": "{Typography.Line Height.140}"
      },
      "Tracking": {
        "$extensions": {
          "com.figma.scopes": [
            "LETTER_SPACING",
            "PARAGRAPH_SPACING",
            "PARAGRAPH_INDENT"
          ],
          "com.figma.hiddenFromPublishing": true
        },
        "$type": "number",
        "$value": "{Typography.Tracking.None}"
      }
    },
    "Paragraph": {
      "FontFamily": {
        "$extensions": {
          "com.figma.scopes": [
            "FONT_FAMILY"
          ],
          "com.figma.hiddenFromPublishing": true
        },
        "$type": "text",
        "$value": "{Typography.Font Family.Plain}"
      },
      "FontSize": {
        "$extensions": {
          "com.figma.scopes": [
            "FONT_SIZE"
          ],
          "com.figma.hiddenFromPublishing": true
        },
        "$type": "number",
        "$value": "{Typography.Font Size.100}"
      },
      "LineHeight": {
        "$extensions": {
          "com.figma.scopes": [
            "LINE_HEIGHT"
          ],
          "com.figma.hiddenFromPublishing": true
        },
        "$type": "number",
        "$value": "{Typography.Line Height.140}"
      },
      "Tracking": {
        "$extensions": {
          "com.figma.scopes": [
            "LETTER_SPACING",
            "PARAGRAPH_SPACING",
            "PARAGRAPH_INDENT"
          ],
          "com.figma.hiddenFromPublishing": true
        },
        "$type": "number",
        "$value": "{Typography.Tracking.None}"
      }
    },
    "Caption-lg": {
      "FontFamily": {
        "$extensions": {
          "com.figma.scopes": [
            "FONT_FAMILY"
          ],
          "com.figma.hiddenFromPublishing": true
        },
        "$type": "text",
        "$value": "{Typography.Font Family.Plain}"
      },
      "FontSize": {
        "$extensions": {
          "com.figma.scopes": [
            "FONT_SIZE"
          ],
          "com.figma.hiddenFromPublishing": true
        },
        "$type": "number",
        "$value": "{Typography.Font Size.90}"
      },
      "LineHeight": {
        "$extensions": {
          "com.figma.scopes": [
            "LINE_HEIGHT"
          ],
          "com.figma.hiddenFromPublishing": true
        },
        "$type": "number",
        "$value": "{Typography.Line Height.100}"
      },
      "Tracking": {
        "$extensions": {
          "com.figma.scopes": [
            "LETTER_SPACING",
            "PARAGRAPH_SPACING",
            "PARAGRAPH_INDENT"
          ],
          "com.figma.hiddenFromPublishing": true
        },
        "$type": "number",
        "$value": "{Typography.Tracking.None}"
      }
    },
    "Caption-md": {
      "FontFamily": {
        "$extensions": {
          "com.figma.scopes": [
            "FONT_FAMILY"
          ],
          "com.figma.hiddenFromPublishing": true
        },
        "$type": "text",
        "$value": "{Typography.Font Family.Plain}"
      },
      "FontSize": {
        "$extensions": {
          "com.figma.scopes": [
            "FONT_SIZE"
          ],
          "com.figma.hiddenFromPublishing": true
        },
        "$type": "number",
        "$value": "{Typography.Font Size.80}"
      },
      "LineHeight": {
        "$extensions": {
          "com.figma.scopes": [
            "LINE_HEIGHT"
          ],
          "com.figma.hiddenFromPublishing": true
        },
        "$type": "number",
        "$value": "{Typography.Line Height.100}"
      },
      "Tracking": {
        "$extensions": {
          "com.figma.scopes": [
            "LETTER_SPACING",
            "PARAGRAPH_SPACING",
            "PARAGRAPH_INDENT"
          ],
          "com.figma.hiddenFromPublishing": true
        },
        "$type": "number",
        "$value": "{Typography.Tracking.None}"
      }
    },
    "Caption-sm": {
      "FontFamily": {
        "$extensions": {
          "com.figma.scopes": [
            "FONT_FAMILY"
          ],
          "com.figma.hiddenFromPublishing": true
        },
        "$type": "text",
        "$value": "{Typography.Font Family.Plain}"
      },
      "FontSize": {
        "$extensions": {
          "com.figma.scopes": [
            "FONT_SIZE"
          ],
          "com.figma.hiddenFromPublishing": true
        },
        "$type": "number",
        "$value": "{Typography.Font Size.70}"
      },
      "LineHeight": {
        "$extensions": {
          "com.figma.scopes": [
            "LINE_HEIGHT"
          ],
          "com.figma.hiddenFromPublishing": true
        },
        "$type": "number",
        "$value": "{Typography.Line Height.100}"
      },
      "Tracking": {
        "$extensions": {
          "com.figma.scopes": [
            "LETTER_SPACING",
            "PARAGRAPH_SPACING",
            "PARAGRAPH_INDENT"
          ],
          "com.figma.hiddenFromPublishing": true
        },
        "$type": "number",
        "$value": "{Typography.Tracking.None}"
      }
    },
    "Caption-xs": {
      "FontFamily": {
        "$extensions": {
          "com.figma.scopes": [
            "FONT_FAMILY"
          ],
          "com.figma.hiddenFromPublishing": true
        },
        "$type": "text",
        "$value": "{Typography.Font Family.Plain}"
      },
      "FontSize": {
        "$extensions": {
          "com.figma.scopes": [
            "FONT_SIZE"
          ],
          "com.figma.hiddenFromPublishing": true
        },
        "$type": "number",
        "$value": "{Typography.Font Size.60}"
      },
      "LineHeight": {
        "$extensions": {
          "com.figma.scopes": [
            "LINE_HEIGHT"
          ],
          "com.figma.hiddenFromPublishing": true
        },
        "$type": "number",
        "$value": "{Typography.Line Height.80}"
      },
      "Tracking": {
        "$extensions": {
          "com.figma.scopes": [
            "LETTER_SPACING",
            "PARAGRAPH_SPACING",
            "PARAGRAPH_INDENT"
          ],
          "com.figma.hiddenFromPublishing": true
        },
        "$type": "number",
        "$value": "{Typography.Tracking.None}"
      }
    }
  }
}